litecache/__init__.py
litecache/parser.py
litecache/server.py
litecache2-0.1.5.dist-info/METADATA
litecache2-0.1.5.dist-info/WHEEL
litecache2-0.1.5.dist-info/entry_points.txt
litecache2-0.1.5.dist-info/RECORD
