Metadata-Version: 2.4
Name: litecache2
Version: 0.1.5
Summary: A lightweight async TCP dictionary server with RESP support
Author-email: Joe Pasquantonio <joe.pasquantonio@gmail.com>
Requires-Python: >=3.11
Requires-Dist: click>=8.1.8
Requires-Dist: colorlog>=6.9.0
Requires-Dist: pyyaml>=6.0.2
Requires-Dist: uvloop>=0.21.0
